objprint/__init__.py
objprint/color_util.py
objprint/decorator.py
objprint/frame_analyzer.py
objprint/objprint.py
objprint/executing/__init__.py
objprint/executing/_exceptions.py
objprint/executing/_position_node_finder.py
objprint/executing/executing.py
objprint/executing/py.typed
objprint-0.3.0.dist-info/LICENSE
objprint-0.3.0.dist-info/METADATA
objprint-0.3.0.dist-info/NOTICE.txt
objprint-0.3.0.dist-info/WHEEL
objprint-0.3.0.dist-info/top_level.txt
objprint-0.3.0.dist-info/RECORD
