Metadata-Version: 2.1
Name: objprint
Version: 0.3.0
Summary: A library that can print Python objects in human readable format
Author-email: Tian Gao <gaogaotiantian@hotmail.com>
License:                                  Apache License
Project-URL: Homepage, https://github.com/gaogaotiantian/objprint
Classifier: Development Status :: 4 - Beta
Classifier: Programming Language :: Python :: 3.9
Classifier: Programming Language :: Python :: 3.10
Classifier: Programming Language :: Python :: 3.11
Classifier: Programming Language :: Python :: 3.12
Classifier: Programming Language :: Python :: 3.13
Classifier: Intended Audience :: Developers
Classifier: License :: OSI Approved :: Apache Software License
Classifier: Operating System :: OS Independent
Requires-Python: >=3.9
License-File: LICENSE
License-File: NOTICE.txt
